README.txt
buildout.cfg
setup.cfg
setup.py
collective/__init__.py
collective.catalogcache.egg-info/PKG-INFO
collective.catalogcache.egg-info/SOURCES.txt
collective.catalogcache.egg-info/dependency_links.txt
collective.catalogcache.egg-info/entry_points.txt
collective.catalogcache.egg-info/namespace_packages.txt
collective.catalogcache.egg-info/not-zip-safe
collective.catalogcache.egg-info/requires.txt
collective.catalogcache.egg-info/top_level.txt
collective/catalogcache/__init__.py
collective/catalogcache/configure.zcml
collective/catalogcache/patch.py
docs/HISTORY.txt