Metadata-Version: 1.0
Name: collective.catalogcache
Version: 0.2
Summary: Cache ZCatalog results with memcached - experimental
Home-page: UNKNOWN
Author: Hedley Roos & Roche Compaan
Author-email: hedley@upfrontsystems.co.za
License: GPL
Platform: UNKNOWN
Classifier: Framework :: Zope2
Classifier: Programming Language :: Python
Classifier: Topic :: Software Development :: Libraries :: Python Modules
